LICENSE.txt
MANIFEST.in
README.md
setup.py
michel/__init__.py
michel/michel.py
michel.egg-info/PKG-INFO
michel.egg-info/SOURCES.txt
michel.egg-info/dependency_links.txt
michel.egg-info/entry_points.txt
michel.egg-info/requires.txt
michel.egg-info/top_level.txt