Metadata-Version: 1.0
Name: michel
Version: 0.0.5
Summary: pushes/pull flat text files to google tasks
Home-page: https://github.com/chmduquesne/michel
Author: Christophe-Marie Duquesne
Author-email: chm.duquesne@gmail.com
License: This software is public domain.
